decoder_10output.v
module decoder_10output(
    input [4:0] q,
    output reg [9:0] out
);
    
    always @(*) begin
        case (q)
            5'b00000: out = 10'b0000000001;
            5'b00001: out = 10'b0000000010;
            5'b00011: out = 10'b0000000100;
            5'b00111: out = 10'b0000001000;
            5'b01111: out = 10'b0000010000;
            5'b11111: out = 10'b0000100000;
            5'b11110: out = 10'b0001000000;
            5'b11100: out = 10'b0010000000;
            5'b11000: out = 10'b0100000000;
            5'b10000: out = 10'b1000000000;
            default:  out = 10'b0000000001;
        endcase
    end
    
endmodule

dff_with_reset.v
module dff_with_reset(
    input clk,
    input reset,
    input d,
    output reg q,
    output qn
);
    
    always @(posedge clk or posedge reset) begin
        if (reset)
            q <= 1'b0;
        else
            q <= d;
    end
    
    assign qn = ~q;
    
endmodule

johnson_counter_5stage.v
module johnson_counter_5stage(
    input clk,
    input reset,
    output [4:0] q
);
    
    wire [4:0] qn;
    wire feedback;
    
    assign feedback = ~q[4];
    
    dff_with_reset stage0 (.clk(clk), .reset(reset), .d(feedback), .q(q[0]), .qn(qn[0]));
    dff_with_reset stage1 (.clk(clk), .reset(reset), .d(q[0]), .q(q[1]), .qn(qn[1]));
    dff_with_reset stage2 (.clk(clk), .reset(reset), .d(q[1]), .q(q[2]), .qn(qn[2]));
    dff_with_reset stage3 (.clk(clk), .reset(reset), .d(q[2]), .q(q[3]), .qn(qn[3]));
    dff_with_reset stage4 (.clk(clk), .reset(reset), .d(q[3]), .q(q[4]), .qn(qn[4]));
    
endmodule

clock_control.v
module clock_control(
    input clk_in,
    input clk_inhibit,
    input reset,
    output clk_out
);
    
    assign clk_out = clk_in & ~clk_inhibit & ~reset;
    
endmodule

cd4017_top.v
module cd4017_top(
    input clk,
    input reset,
    input clk_inhibit,
    output [9:0] Q,
    output carry_out
);
    
    wire gated_clk;
    wire [4:0] counter_state;
    
    clock_control clk_ctrl (
        .clk_in(clk),
        .clk_inhibit(clk_inhibit),
        .reset(reset),
        .clk_out(gated_clk)
    );
    
    johnson_counter_5stage counter (
        .clk(gated_clk),
        .reset(reset),
        .q(counter_state)
    );
    
    decoder_10output decoder (
        .q(counter_state),
        .out(Q)
    );
    
    assign carry_out = Q[9];
    
endmodule

code_lock_system.v
module code_lock_system(
    input [4:0] keys,        // keys[0]=A, keys[1]=B, keys[2]=C, keys[3]=D, keys[4]=E
    input reset,             // Master reset (active HIGH)
    output lock_open,        // HIGH when correct sequence completed
    output alarm,            // HIGH when wrong key pressed
    output [4:0] stage_leds  // stage_leds[i] = stage i is active
);

    wire [9:0] q1, q2, q3, q4, q5;
    wire system_reset;
    reg lock_open_reg;
    reg alarm_reg;

    // Combined reset: Master reset or Alarm
    assign system_reset = reset || alarm_reg;

    // CD4017 Stage Instantiations
    // Stage 1: always enabled
    cd4017_top stage1 (
        .clk(keys[0]),
        .reset(system_reset),
        .clk_inhibit(1'b0),
        .Q(q1),
        .carry_out()
    );

    // Stage 2: enabled only when stage1 complete
    cd4017_top stage2 (
        .clk(keys[1]),
        .reset(system_reset),
        .clk_inhibit(~q1[1]),
        .Q(q2),
        .carry_out()
    );

    // Stage 3: enabled only when stage2 complete AND key B is released (prevents ripple)
    cd4017_top stage3 (
        .clk(keys[1]),
        .reset(system_reset),
        .clk_inhibit(~q2[1] | keys[1]), // Interlock on keys[1] to prevent same-cycle ripple
        .Q(q3),
        .carry_out()
    );

    // Stage 4: enabled only when stage3 complete
    cd4017_top stage4 (
        .clk(keys[2]),
        .reset(system_reset),
        .clk_inhibit(~q3[1]),
        .Q(q4),
        .carry_out()
    );

    // Stage 5: enabled only when stage4 complete
    cd4017_top stage5 (
        .clk(keys[3]),
        .reset(system_reset),
        .clk_inhibit(~q4[1]),
        .Q(q5),
        .carry_out()
    );

    // Stage active detection signals
    wire stage1_active, stage2_active, stage3_active, stage4_active, stage5_active;

    // A stage is active when previous stage completed but current stage hasn't 
    assign stage1_active = (q1[0] == 1'b1);                                     // Stage 1 at reset position
    assign stage2_active = (q1[1] == 1'b1) && (q2[1] == 1'b0);                  // Stage1 done, stage2 not done
    assign stage3_active = (q2[1] == 1'b1) && (q3[1] == 1'b0);                  // Stage2 done, stage3 not done  
    assign stage4_active = (q3[1] == 1'b1) && (q4[1] == 1'b0);                  // Stage3 done, stage4 not done
    assign stage5_active = (q4[1] == 1'b1) && (q5[1] == 1'b0);                  // Stage4 done, stage5 not done

    // Alarm logic (Registered to avoid race conditions with stage transitions)
    // We sample the "active" status on the positive edge of the keys.
    // This ensures we see the state BEFORE the current key press advances the counter.
    always @(posedge keys[0] or posedge keys[1] or posedge keys[2] or 
             posedge keys[3] or posedge keys[4] or posedge reset) begin
        if (reset) begin
            alarm_reg <= 1'b0;
        end else if (!alarm_reg) begin
            // Check if the pressed key is valid for any currently active stage
            if (keys[0] && !stage1_active) 
                alarm_reg <= 1'b1;
            else if (keys[1] && !(stage2_active || stage3_active)) 
                alarm_reg <= 1'b1;
            else if (keys[2] && !stage4_active) 
                alarm_reg <= 1'b1;
            else if (keys[3] && !stage5_active) 
                alarm_reg <= 1'b1;
            else if (keys[4] && (q5[1] == 1'b0)) 
                alarm_reg <= 1'b1;
        end
    end
    assign alarm = alarm_reg;

    // Stage Active Indicators
    assign stage_leds[0] = stage1_active;
    assign stage_leds[1] = stage2_active;
    assign stage_leds[2] = stage3_active;
    assign stage_leds[3] = stage4_active;
    assign stage_leds[4] = stage5_active;

    // Success Detection (Key E)
    always @(posedge keys[4] or posedge reset) begin
        if (reset)
            lock_open_reg <= 1'b0;
        else if (q5[1] == 1'b1 && !alarm_reg)
            lock_open_reg <= 1'b1;
    end
    assign lock_open = lock_open_reg;

endmodule

code_lock_tb.v
`timescale 1ns / 1ps

module code_lock_tb;
    reg [4:0] keys;
    reg reset;
    wire lock_open;
    wire alarm;
    wire [4:0] stage_leds;
    
    // Instantiate code lock
    code_lock_system uut (
        .keys(keys),
        .reset(reset),
        .lock_open(lock_open),
        .alarm(alarm),
        .stage_leds(stage_leds)
    );

    // Task to press a key with realistic timing
    task press_key;
        input [2:0] key_num;  // 0=A, 1=B, 2=C, 3=D, 4=E
        begin
            $display("[%0t] Pressing Key %s", $time, 
                     key_num==0?"A":key_num==1?"B":key_num==2?"C":key_num==3?"D":"E");
            keys[key_num] = 1'b1;  // Press
            #100;                   // Hold for 100ns
            keys[key_num] = 1'b0;  // Release
            #100;                   // Wait before next press
        end
    endtask

    // Task to apply reset
    task apply_reset;
        begin
            $display("[%0t] Applying RESET", $time);
            reset = 1'b1;
            #50;
            reset = 1'b0;
            #50;
            $display("[%0t] Reset released", $time);
        end
    endtask

    initial begin
        // Initialize
        keys = 5'b00000;
        reset = 1'b0;
        
        $display("\n========================================");
        $display("Starting Code Lock Testbench");
        $display("Correct Code: A -> B -> B -> C -> D -> E");
        $display("========================================\n");
        
        // TEST 1: Correct sequence
        $display("\n--- TEST 1: Correct Sequence ---");
        apply_reset();
        press_key(0);  // A
        press_key(1);  // B
        press_key(1);  // B again
        press_key(2);  // C
        press_key(3);  // D
        press_key(4);  // E
        #100;
        if (lock_open && !alarm)
            $display("✓ TEST 1 PASSED: Lock opened successfully");
        else
            $display("✗ TEST 1 FAILED: lock_open=%b, alarm=%b", lock_open, alarm);
        
        // TEST 2: Wrong first key
        $display("\n--- TEST 2: Wrong First Key (B instead of A) ---");
        apply_reset();
        press_key(1);  // B (wrong!)
        #100;
        if (alarm && !lock_open)
            $display("✓ TEST 2 PASSED: Alarm triggered correctly");
        else
            $display("✗ TEST 2 FAILED: alarm=%b, lock_open=%b", alarm, lock_open);
        
        // TEST 3: Wrong key at stage 2
        $display("\n--- TEST 3: Wrong Key at Stage 2 ---");
        apply_reset();
        press_key(0);  // A (correct)
        press_key(2);  // C (wrong! should be B)
        #100;
        if (alarm && !lock_open)
            $display("✓ TEST 3 PASSED: Alarm triggered correctly");
        else
            $display("✗ TEST 3 FAILED: alarm=%b", alarm);
        
        // TEST 4: Skipping second B press
        $display("\n--- TEST 4: Skipping Second B Press ---");
        apply_reset();
        press_key(0);  // A
        press_key(1);  // B (first)
        press_key(2);  // C (skipped second B!)
        #100;
        if (alarm)
            $display("✓ TEST 4 PASSED: Detected skipped stage");
        else
            $display("✗ TEST 4 FAILED");
        
        // TEST 5: Pressing E too early
        $display("\n--- TEST 5: Pressing E Too Early ---");
        apply_reset();
        press_key(0);  // A
        press_key(1);  // B
        press_key(4);  // E (too early!)
        #100;
        if (alarm)
            $display("✓ TEST 5 PASSED: Early unlock prevented");
        else
            $display("✗ TEST 5 FAILED");
        
        // TEST 6: Reset mid-sequence and retry
        $display("\n--- TEST 6: Reset Mid-Sequence and Retry ---");
        apply_reset();
        press_key(0);  // A
        press_key(1);  // B
        $display("[%0t] Interrupting with reset...", $time);
        apply_reset();
        // Retry full sequence
        press_key(0);  // A
        press_key(1);  // B
        press_key(1);  // B
        press_key(2);  // C
        press_key(3);  // D
        press_key(4);  // E
        #100;
        if (lock_open && !alarm)
            $display("✓ TEST 6 PASSED: System recovered after reset");
        else
            $display("✗ TEST 6 FAILED");

        // TEST 7: Multiple Wrong Attempts
        $display("\n--- TEST 7: Multiple Wrong Attempts ---");
        apply_reset();
        press_key(0);  // A
        press_key(2);  // C (wrong)
        #100;
        if (alarm) $display("✓ Attempt 1 caught alarm");
        apply_reset();
        press_key(0);  // A
        press_key(1);  // B
        press_key(2);  // C (skipped B)
        #100;
        if (alarm) $display("✓ Attempt 2 caught alarm");
        apply_reset();
        press_key(0);  // A
        press_key(1);  // B
        press_key(1);  // B
        press_key(2);  // C
        press_key(3);  // D
        press_key(4);  // E
        #100;
        if (lock_open && !alarm)
            $display("✓ TEST 7 PASSED: System worked after multiple failures");
        else
            $display("✗ TEST 7 FAILED");
        
        $display("\n========================================");
        $display("All tests completed");
        $display("========================================\n");
        
        #500;
        $finish;
    end

    // Continuous monitoring
    initial begin
        $monitor("Time=%0t | Keys=%b | Stage LEDs=%b | Alarm=%b | Lock=%b", 
                 $time, keys, stage_leds, alarm, lock_open);
    end

    // Waveform dump for GTKWave/ModelSim
    initial begin
        $dumpfile("code_lock.vcd");
        $dumpvars(0, code_lock_tb);
        $dumpvars(0, uut.stage1);
        $dumpvars(0, uut.stage2);
        $dumpvars(0, uut.stage3);
        $dumpvars(0, uut.stage4);
        $dumpvars(0, uut.stage5);
    end

    // Display stage transitions
    always @(stage_leds) begin
        $display("[%0t] Stage LEDs changed: %b", $time, stage_leds);
    end

    always @(posedge alarm) begin
        $display("[%0t] ⚠️  ALARM TRIGGERED!", $time);
    end

    always @(posedge lock_open) begin
        $display("[%0t] 🔓 LOCK OPENED!", $time);
    end

endmodule

code_lock.vcd
$date
	Mon Apr  6 02:01:36 2026
$end
$version
	Icarus Verilog
$end
$timescale
	1ps
$end
$scope module code_lock_tb $end
$var wire 5 ! stage_leds [4:0] $end
$var wire 1 " lock_open $end
$var wire 1 # alarm $end
$var reg 5 $ keys [4:0] $end
$var reg 1 % reset $end
$scope module uut $end
$var wire 1 # alarm $end
$var wire 5 & keys [4:0] $end
$var wire 1 " lock_open $end
$var wire 1 % reset $end
$var wire 1 ' stage1_active $end
$var wire 1 ( stage2_active $end
$var wire 1 ) stage3_active $end
$var wire 1 * stage4_active $end
$var wire 1 + stage5_active $end
$var wire 1 , system_reset $end
$var wire 5 - stage_leds [4:0] $end
$var wire 10 . q5 [9:0] $end
$var wire 10 / q4 [9:0] $end
$var wire 10 0 q3 [9:0] $end
$var wire 10 1 q2 [9:0] $end
$var wire 10 2 q1 [9:0] $end
$var reg 1 3 alarm_reg $end
$var reg 1 4 lock_open_reg $end
$scope module stage1 $end
$var wire 1 5 clk $end
$var wire 1 6 clk_inhibit $end
$var wire 1 , reset $end
$var wire 1 7 gated_clk $end
$var wire 5 8 counter_state [4:0] $end
$var wire 1 9 carry_out $end
$var wire 10 : Q [9:0] $end
$scope module clk_ctrl $end
$var wire 1 5 clk_in $end
$var wire 1 6 clk_inhibit $end
$var wire 1 7 clk_out $end
$var wire 1 , reset $end
$upscope $end
$scope module counter $end
$var wire 1 7 clk $end
$var wire 1 ; feedback $end
$var wire 1 , reset $end
$var wire 5 < qn [4:0] $end
$var wire 5 = q [4:0] $end
$scope module stage0 $end
$var wire 1 7 clk $end
$var wire 1 ; d $end
$var wire 1 > qn $end
$var wire 1 , reset $end
$var reg 1 ? q $end
$upscope $end
$scope module stage1 $end
$var wire 1 7 clk $end
$var wire 1 @ d $end
$var wire 1 A qn $end
$var wire 1 , reset $end
$var reg 1 B q $end
$upscope $end
$scope module stage2 $end
$var wire 1 7 clk $end
$var wire 1 C d $end
$var wire 1 D qn $end
$var wire 1 , reset $end
$var reg 1 E q $end
$upscope $end
$scope module stage3 $end
$var wire 1 7 clk $end
$var wire 1 F d $end
$var wire 1 G qn $end
$var wire 1 , reset $end
$var reg 1 H q $end
$upscope $end
$scope module stage4 $end
$var wire 1 7 clk $end
$var wire 1 I d $end
$var wire 1 J qn $end
$var wire 1 , reset $end
$var reg 1 K q $end
$upscope $end
$upscope $end
$scope module decoder $end
$var wire 5 L q [4:0] $end
$var reg 10 M out [9:0] $end
$upscope $end
$upscope $end
$scope module stage2 $end
$var wire 1 N clk $end
$var wire 1 O clk_inhibit $end
$var wire 1 , reset $end
$var wire 1 P gated_clk $end
$var wire 5 Q counter_state [4:0] $end
$var wire 1 R carry_out $end
$var wire 10 S Q [9:0] $end
$scope module clk_ctrl $end
$var wire 1 N clk_in $end
$var wire 1 O clk_inhibit $end
$var wire 1 P clk_out $end
$var wire 1 , reset $end
$upscope $end
$scope module counter $end
$var wire 1 P clk $end
$var wire 1 T feedback $end
$var wire 1 , reset $end
$var wire 5 U qn [4:0] $end
$var wire 5 V q [4:0] $end
$scope module stage0 $end
$var wire 1 P clk $end
$var wire 1 T d $end
$var wire 1 W qn $end
$var wire 1 , reset $end
$var reg 1 X q $end
$upscope $end
$scope module stage1 $end
$var wire 1 P clk $end
$var wire 1 Y d $end
$var wire 1 Z qn $end
$var wire 1 , reset $end
$var reg 1 [ q $end
$upscope $end
$scope module stage2 $end
$var wire 1 P clk $end
$var wire 1 \ d $end
$var wire 1 ] qn $end
$var wire 1 , reset $end
$var reg 1 ^ q $end
$upscope $end
$scope module stage3 $end
$var wire 1 P clk $end
$var wire 1 _ d $end
$var wire 1 ` qn $end
$var wire 1 , reset $end
$var reg 1 a q $end
$upscope $end
$scope module stage4 $end
$var wire 1 P clk $end
$var wire 1 b d $end
$var wire 1 c qn $end
$var wire 1 , reset $end
$var reg 1 d q $end
$upscope $end
$upscope $end
$scope module decoder $end
$var wire 5 e q [4:0] $end
$var reg 10 f out [9:0] $end
$upscope $end
$upscope $end
$scope module stage3 $end
$var wire 1 g clk $end
$var wire 1 h clk_inhibit $end
$var wire 1 , reset $end
$var wire 1 i gated_clk $end
$var wire 5 j counter_state [4:0] $end
$var wire 1 k carry_out $end
$var wire 10 l Q [9:0] $end
$scope module clk_ctrl $end
$var wire 1 g clk_in $end
$var wire 1 h clk_inhibit $end
$var wire 1 i clk_out $end
$var wire 1 , reset $end
$upscope $end
$scope module counter $end
$var wire 1 i clk $end
$var wire 1 m feedback $end
$var wire 1 , reset $end
$var wire 5 n qn [4:0] $end
$var wire 5 o q [4:0] $end
$scope module stage0 $end
$var wire 1 i clk $end
$var wire 1 m d $end
$var wire 1 p qn $end
$var wire 1 , reset $end
$var reg 1 q q $end
$upscope $end
$scope module stage1 $end
$var wire 1 i clk $end
$var wire 1 r d $end
$var wire 1 s qn $end
$var wire 1 , reset $end
$var reg 1 t q $end
$upscope $end
$scope module stage2 $end
$var wire 1 i clk $end
$var wire 1 u d $end
$var wire 1 v qn $end
$var wire 1 , reset $end
$var reg 1 w q $end
$upscope $end
$scope module stage3 $end
$var wire 1 i clk $end
$var wire 1 x d $end
$var wire 1 y qn $end
$var wire 1 , reset $end
$var reg 1 z q $end
$upscope $end
$scope module stage4 $end
$var wire 1 i clk $end
$var wire 1 { d $end
$var wire 1 | qn $end
$var wire 1 , reset $end
$var reg 1 } q $end
$upscope $end
$upscope $end
$scope module decoder $end
$var wire 5 ~ q [4:0] $end
$var reg 10 !" out [9:0] $end
$upscope $end
$upscope $end
$scope module stage4 $end
$var wire 1 "" clk $end
$var wire 1 #" clk_inhibit $end
$var wire 1 , reset $end
$var wire 1 $" gated_clk $end
$var wire 5 %" counter_state [4:0] $end
$var wire 1 &" carry_out $end
$var wire 10 '" Q [9:0] $end
$scope module clk_ctrl $end
$var wire 1 "" clk_in $end
$var wire 1 #" clk_inhibit $end
$var wire 1 $" clk_out $end
$var wire 1 , reset $end
$upscope $end
$scope module counter $end
$var wire 1 $" clk $end
$var wire 1 (" feedback $end
$var wire 1 , reset $end
$var wire 5 )" qn [4:0] $end
$var wire 5 *" q [4:0] $end
$scope module stage0 $end
$var wire 1 $" clk $end
$var wire 1 (" d $end
$var wire 1 +" qn $end
$var wire 1 , reset $end
$var reg 1 ," q $end
$upscope $end
$scope module stage1 $end
$var wire 1 $" clk $end
$var wire 1 -" d $end
$var wire 1 ." qn $end
$var wire 1 , reset $end
$var reg 1 /" q $end
$upscope $end
$scope module stage2 $end
$var wire 1 $" clk $end
$var wire 1 0" d $end
$var wire 1 1" qn $end
$var wire 1 , reset $end
$var reg 1 2" q $end
$upscope $end
$scope module stage3 $end
$var wire 1 $" clk $end
$var wire 1 3" d $end
$var wire 1 4" qn $end
$var wire 1 , reset $end
$var reg 1 5" q $end
$upscope $end
$scope module stage4 $end
$var wire 1 $" clk $end
$var wire 1 6" d $end
$var wire 1 7" qn $end
$var wire 1 , reset $end
$var reg 1 8" q $end
$upscope $end
$upscope $end
$scope module decoder $end
$var wire 5 9" q [4:0] $end
$var reg 10 :" out [9:0] $end
$upscope $end
$upscope $end
$scope module stage5 $end
$var wire 1 ;" clk $end
$var wire 1 <" clk_inhibit $end
$var wire 1 , reset $end
$var wire 1 =" gated_clk $end
$var wire 5 >" counter_state [4:0] $end
$var wire 1 ?" carry_out $end
$var wire 10 @" Q [9:0] $end
$scope module clk_ctrl $end
$var wire 1 ;" clk_in $end
$var wire 1 <" clk_inhibit $end
$var wire 1 =" clk_out $end
$var wire 1 , reset $end
$upscope $end
$scope module counter $end
$var wire 1 =" clk $end
$var wire 1 A" feedback $end
$var wire 1 , reset $end
$var wire 5 B" qn [4:0] $end
$var wire 5 C" q [4:0] $end
$scope module stage0 $end
$var wire 1 =" clk $end
$var wire 1 A" d $end
$var wire 1 D" qn $end
$var wire 1 , reset $end
$var reg 1 E" q $end
$upscope $end
$scope module stage1 $end
$var wire 1 =" clk $end
$var wire 1 F" d $end
$var wire 1 G" qn $end
$var wire 1 , reset $end
$var reg 1 H" q $end
$upscope $end
$scope module stage2 $end
$var wire 1 =" clk $end
$var wire 1 I" d $end
$var wire 1 J" qn $end
$var wire 1 , reset $end
$var reg 1 K" q $end
$upscope $end
$scope module stage3 $end
$var wire 1 =" clk $end
$var wire 1 L" d $end
$var wire 1 M" qn $end
$var wire 1 , reset $end
$var reg 1 N" q $end
$upscope $end
$scope module stage4 $end
$var wire 1 =" clk $end
$var wire 1 O" d $end
$var wire 1 P" qn $end
$var wire 1 , reset $end
$var reg 1 Q" q $end
$upscope $end
$upscope $end
$scope module decoder $end
$var wire 5 R" q [4:0] $end
$var reg 10 S" out [9:0] $end
$upscope $end
$upscope $end
$upscope $end
$scope task apply_reset $end
$upscope $end
$scope task press_key $end
$var reg 3 T" key_num [2:0] $end
$upscope $end
$upscope $end
$scope module code_lock_tb $end
$scope module uut $end
$scope module stage1 $end
$scope module clk_ctrl $end
$upscope $end
$scope module counter $end
$scope module stage0 $end
$upscope $end
$scope module stage1 $end
$upscope $end
$scope module stage2 $end
$upscope $end
$scope module stage3 $end
$upscope $end
$scope module stage4 $end
$upscope $end
$upscope $end
$scope module decoder $end
$upscope $end
$upscope $end
$upscope $end
$upscope $end
$scope module code_lock_tb $end
$scope module uut $end
$scope module stage2 $end
$scope module clk_ctrl $end
$upscope $end
$scope module counter $end
$scope module stage0 $end
$upscope $end
$scope module stage1 $end
$upscope $end
$scope module stage2 $end
$upscope $end
$scope module stage3 $end
$upscope $end
$scope module stage4 $end
$upscope $end
$upscope $end
$scope module decoder $end
$upscope $end
$upscope $end
$upscope $end
$upscope $end
$scope module code_lock_tb $end
$scope module uut $end
$scope module stage3 $end
$scope module clk_ctrl $end
$upscope $end
$scope module counter $end
$scope module stage0 $end
$upscope $end
$scope module stage1 $end
$upscope $end
$scope module stage2 $end
$upscope $end
$scope module stage3 $end
$upscope $end
$scope module stage4 $end
$upscope $end
$upscope $end
$scope module decoder $end
$upscope $end
$upscope $end
$upscope $end
$upscope $end
$scope module code_lock_tb $end
$scope module uut $end
$scope module stage4 $end
$scope module clk_ctrl $end
$upscope $end
$scope module counter $end
$scope module stage0 $end
$upscope $end
$scope module stage1 $end
$upscope $end
$scope module stage2 $end
$upscope $end
$scope module stage3 $end
$upscope $end
$scope module stage4 $end
$upscope $end
$upscope $end
$scope module decoder $end
$upscope $end
$upscope $end
$upscope $end
$upscope $end
$scope module code_lock_tb $end
$scope module uut $end
$scope module stage5 $end
$scope module clk_ctrl $end
$upscope $end
$scope module counter $end
$scope module stage0 $end
$upscope $end
$scope module stage1 $end
$upscope $end
$scope module stage2 $end
$upscope $end
$scope module stage3 $end
$upscope $end
$scope module stage4 $end
$upscope $end
$upscope $end
$scope module decoder $end
$upscope $end
$upscope $end
$upscope $end
$upscope $end
$enddefinitions $end
$comment Show the parameter values. $end
$dumpall
$end
#0
$dumpvars
bx T"
b1 S"
b0 R"
0Q"
1P"
0O"
0N"
1M"
0L"
0K"
1J"
0I"
0H"
1G"
0F"
0E"
1D"
b0 C"
b11111 B"
1A"
b1 @"
0?"
b0 >"
0="
1<"
0;"
b1 :"
b0 9"
08"
17"
06"
05"
14"
03"
02"
11"
00"
0/"
1."
0-"
0,"
1+"
b0 *"
b11111 )"
1("
b1 '"
0&"
b0 %"
0$"
1#"
0""
b1 !"
b0 ~
0}
1|
0{
0z
1y
0x
0w
1v
0u
0t
1s
0r
0q
1p
b0 o
b11111 n
1m
b1 l
0k
b0 j
0i
1h
0g
b1 f
b0 e
0d
1c
0b
0a
1`
0_
0^
1]
0\
0[
1Z
0Y
0X
1W
b0 V
b11111 U
1T
b1 S
0R
b0 Q
0P
1O
0N
b1 M
b0 L
0K
1J
0I
0H
1G
0F
0E
1D
0C
0B
1A
0@
0?
1>
b0 =
b11111 <
1;
b1 :
09
b0 8
07
06
05
04
03
b1 2
b1 1
b1 0
b1 /
b1 .
b1 -
1,
0+
0*
0)
0(
1'
b0 &
1%
b0 $
0#
0"
b1 !
$end
#50000
0,
0%
#100000
b10 !
b10 -
1(
0'
0O
b11110 <
1@
b10 2
b10 :
b10 M
b1 8
b1 =
b1 L
0>
1?
17
15
b1 $
b1 &
b0 T"
#200000
07
05
b0 $
b0 &
#300000
b100 !
b100 -
1)
0(
b11110 U
1Y
b10 1
b10 S
b10 f
b1 Q
b1 V
b1 e
0W
1X
1P
1N
1g
b10 $
b10 &
b1 T"
#400000
0P
0h
0N
0g
b0 $
b0 &
#500000
b1010 !
b1010 -
1(
1*
0)
0#"
b11100 U
1\
b100 1
b100 S
b100 f
b11110 n
1r
b10 0
b10 l
b10 !"
b11 Q
b11 V
b11 e
b1 j
b1 o
b1 ~
0Z
0p
1[
1q
1P
0i
1h
1N
1g
b10 $
b10 &
#600000
0P
0N
0g
b0 $
b0 &
#700000
b10010 !
b10010 -
1+
0*
0<"
b11110 )"
1-"
b10 /
b10 '"
b10 :"
b1 %"
b1 *"
b1 9"
0+"
1,"
1$"
1""
b100 $
b100 &
b10 T"
#800000
0$"
0""
b0 $
b0 &
#900000
b10 !
b10 -
0+
b11110 B"
1F"
b10 .
b10 @"
b10 S"
b1 >"
b1 C"
b1 R"
0D"
1E"
1="
1;"
b1000 $
b1000 &
b11 T"
#1000000
0="
0;"
b0 $
b0 &
#1100000
1"
14
b10000 $
b10000 &
b100 T"
#1200000
b0 $
b0 &
#1400000
b1 !
b1 -
0(
1'
1O
1#"
1<"
b11111 <
0@
b1 2
b1 :
b1 M
b11111 U
0\
0Y
b1 1
b1 S
b1 f
b11111 n
0r
b1 0
b1 l
b1 !"
b11111 )"
0-"
b1 /
b1 '"
b1 :"
b11111 B"
0F"
b1 .
b1 @"
b1 S"
b0 8
b0 =
b0 L
b0 Q
b0 V
b0 e
b0 j
b0 o
b0 ~
b0 %"
b0 *"
b0 9"
b0 >"
b0 C"
b0 R"
1>
1Z
1W
1p
1+"
1D"
0?
0[
0X
0q
0,"
0E"
0"
04
1,
1%
#1450000
0,
0%
#1500000
1,
1#
13
1N
1g
b10 $
b10 &
b1 T"
#1600000
0N
0g
b0 $
b0 &
#1800000
0#
03
1%
#1850000
0,
0%
#1900000
b10 !
b10 -
1(
0'
0O
b11110 <
1@
b10 2
b10 :
b10 M
b1 8
b1 =
b1 L
0>
1?
17
15
b1 $
b1 &
b0 T"
#2000000
07
05
b0 $
b0 &
#2100000
b1 !
b1 -
0(
1'
1O
b11111 <
0@
b1 2
b1 :
b1 M
b0 8
b0 =
b0 L
1>
0?
1,
1#
13
1""
b100 $
b100 &
b10 T"
#2200000
0""
b0 $
b0 &
#2400000
0#
03
1%
#2450000
0,
0%
#2500000
b10 !
b10 -
1(
0'
0O
b11110 <
1@
b10 2
b10 :
b10 M
b1 8
b1 =
b1 L
0>
1?
17
15
b1 $
b1 &
b0 T"
#2600000
07
05
b0 $
b0 &
#2700000
b100 !
b100 -
1)
0(
b11110 U
1Y
b10 1
b10 S
b10 f
b1 Q
b1 V
b1 e
0W
1X
1P
1N
1g
b10 $
b10 &
b1 T"
#2800000
0P
0h
0N
0g
b0 $
b0 &
#2900000
b1 !
b1 -
0)
1h
1'
1O
b11111 <
0@
b1 2
b1 :
b1 M
b11111 U
0Y
b1 1
b1 S
b1 f
b0 8
b0 =
b0 L
b0 Q
b0 V
b0 e
1>
1W
0?
0X
1,
1#
13
1""
b100 $
b100 &
b10 T"
#3000000
0""
b0 $
b0 &
#3200000
0#
03
1%
#3250000
0,
0%
#3300000
b10 !
b10 -
1(
0'
0O
b11110 <
1@
b10 2
b10 :
b10 M
b1 8
b1 =
b1 L
0>
1?
17
15
b1 $
b1 &
b0 T"
#3400000
07
05
b0 $
b0 &
#3500000
b100 !
b100 -
1)
0(
b11110 U
1Y
b10 1
b10 S
b10 f
b1 Q
b1 V
b1 e
0W
1X
1P
1N
1g
b10 $
b10 &
b1 T"
#3600000
0P
0h
0N
0g
b0 $
b0 &
#3700000
b1 !
b1 -
0)
1h
1'
1O
b11111 <
0@
b1 2
b1 :
b1 M
b11111 U
0Y
b1 1
b1 S
b1 f
b0 8
b0 =
b0 L
b0 Q
b0 V
b0 e
1>
1W
0?
0X
1,
1#
13
b10000 $
b10000 &
b100 T"
#3800000
b0 $
b0 &
#4000000
0#
03
1%
#4050000
0,
0%
#4100000
b10 !
b10 -
1(
0'
0O
b11110 <
1@
b10 2
b10 :
b10 M
b1 8
b1 =
b1 L
0>
1?
17
15
b1 $
b1 &
b0 T"
#4200000
07
05
b0 $
b0 &
#4300000
b100 !
b100 -
1)
0(
b11110 U
1Y
b10 1
b10 S
b10 f
b1 Q
b1 V
b1 e
0W
1X
1P
1N
1g
b10 $
b10 &
b1 T"
#4400000
0P
0h
0N
0g
b0 $
b0 &
#4500000
b1 !
b1 -
0)
1h
1'
1O
b11111 <
0@
b1 2
b1 :
b1 M
b11111 U
0Y
b1 1
b1 S
b1 f
b0 8
b0 =
b0 L
b0 Q
b0 V
b0 e
1>
1W
0?
0X
1,
1%
#4550000
0,
0%
#4600000
b10 !
b10 -
1(
0'
0O
b11110 <
1@
b10 2
b10 :
b10 M
b1 8
b1 =
b1 L
0>
1?
17
15
b1 $
b1 &
b0 T"
#4700000
07
05
b0 $
b0 &
#4800000
b100 !
b100 -
1)
0(
b11110 U
1Y
b10 1
b10 S
b10 f
b1 Q
b1 V
b1 e
0W
1X
1P
1N
1g
b10 $
b10 &
b1 T"
#4900000
0P
0h
0N
0g
b0 $
b0 &
#5000000
b1010 !
b1010 -
1(
1*
0)
0#"
b11100 U
1\
b100 1
b100 S
b100 f
b11110 n
1r
b10 0
b10 l
b10 !"
b11 Q
b11 V
b11 e
b1 j
b1 o
b1 ~
0Z
0p
1[
1q
1P
0i
1h
1N
1g
b10 $
b10 &
#5100000
0P
0N
0g
b0 $
b0 &
#5200000
b10010 !
b10010 -
1+
0*
0<"
b11110 )"
1-"
b10 /
b10 '"
b10 :"
b1 %"
b1 *"
b1 9"
0+"
1,"
1$"
1""
b100 $
b100 &
b10 T"
#5300000
0$"
0""
b0 $
b0 &
#5400000
b10 !
b10 -
0+
b11110 B"
1F"
b10 .
b10 @"
b10 S"
b1 >"
b1 C"
b1 R"
0D"
1E"
1="
1;"
b1000 $
b1000 &
b11 T"
#5500000
0="
0;"
b0 $
b0 &
#5600000
1"
14
b10000 $
b10000 &
b100 T"
#5700000
b0 $
b0 &
#5900000
b1 !
b1 -
0(
1'
1O
1#"
1<"
b11111 <
0@
b1 2
b1 :
b1 M
b11111 U
0\
0Y
b1 1
b1 S
b1 f
b11111 n
0r
b1 0
b1 l
b1 !"
b11111 )"
0-"
b1 /
b1 '"
b1 :"
b11111 B"
0F"
b1 .
b1 @"
b1 S"
b0 8
b0 =
b0 L
b0 Q
b0 V
b0 e
b0 j
b0 o
b0 ~
b0 %"
b0 *"
b0 9"
b0 >"
b0 C"
b0 R"
1>
1W
1Z
1p
1+"
1D"
0?
0X
0[
0q
0,"
0E"
0"
04
1,
1%
#5950000
0,
0%
